setup.cfg
setup.py
succubus/__init__.py
succubus/daemonize.py
succubus.egg-info/PKG-INFO
succubus.egg-info/SOURCES.txt
succubus.egg-info/dependency_links.txt
succubus.egg-info/requires.txt
succubus.egg-info/top_level.txt
succubus.egg-info/zip-safe