Metadata-Version: 1.1
Name: succubus
Version: 1.0.post297
Summary: Lightweight Python module for daemonizing
Home-page: https://github.com/ImmobilienScout24/succubus
Author: Stefan Neben, Stefan Nordhausen
Author-email: stefan.neben@immobilienscout24.de, stefan.nordhausen@immobilienscout24.de
License: Apache License 2.0
Platform: UNKNOWN
Classifier: Development Status :: 3 - Alpha
Classifier: Programming Language :: Python
